BoxAnova/__init__.py
BoxAnova/BoxAnova.py
BoxAnova/utils/__init__.py
BoxAnova/utils/renaming.py
boxanova-0.1.12.dist-info/METADATA
boxanova-0.1.12.dist-info/WHEEL
boxanova-0.1.12.dist-info/RECORD
